{
    "relationships": [
        {
            "relationshipId": 1,
            "relationshipName": "user",
            "otherEntityName": "user",
            "relationshipType": "many-to-one",
            "otherEntityField": "login"
        }
    ],
    "fields": [
        {
            "fieldId": 1,
            "fieldName": "timestamp",
            "fieldType": "DateTime",
            "fieldValidateRules": [
                "required"
            ]
        },
        {
            "fieldId": 2,
            "fieldName": "weight",
            "fieldType": "Double",
            "fieldValidateRules": [
                "required"
            ]
        }
    ],
    "changelogDate": "20150818155114",
    "dto": "no",
    "pagination": "infinite-scroll"
}
